<?xml version="1.0" encoding="utf-8"?><resourceInfo xmlns="http://www.ilsp.gr/META-XMLSchema" xmlns:xsi="http://www.w3.org/2001/XMLSchema-instance" xsi:schemaLocation="http://www.ilsp.gr/META-XMLSchema http://metashare.ilsp.gr/META-XMLSchema/v3.0/META-SHARE-Resource.xsd"><identificationInfo><resourceName lang="de">res-name-2</resourceName><resourceName lang="en">full-corpus-image</resourceName><description lang="de">res-descr-2</description><description lang="en">res-descr-1</description><resourceShortName lang="de">res-short-2</resourceShortName><resourceShortName lang="en">res-short-1</resourceShortName><url>http://000-url.test.de</url><url>http://001-url.test.de</url><metaShareId>NOT_DEFINED_FOR_V2</metaShareId><identifier>res-id-1</identifier><identifier>res-id-2</identifier></identificationInfo><distributionInfo><availability>available-restrictedUse</availability><licenceInfo><licence>AGPL</licence><licence>ApacheLicence_2.0</licence><restrictionsOfUse>academic-nonCommercialUse</restrictionsOfUse><restrictionsOfUse>attribution</restrictionsOfUse><distributionAccessMedium>accessibleThroughInterface</distributionAccessMedium><distributionAccessMedium>bluRay</distributionAccessMedium><downloadLocation>http://002-url.test.de</downloadLocation><downloadLocation>http://003-url.test.de</downloadLocation><executionLocation>http://004-url.test.de</executionLocation><executionLocation>http://005-url.test.de</executionLocation><fee>res-dist-fee</fee><attributionText lang="de">res-attr-text-2</attributionText><attributionText lang="en">res-attr-text-1</attributionText><licensor><personInfo><surname lang="en">p005-Surname-1</surname><givenName lang="en">p005-Given name-1</givenName><sex>female</sex><communicationInfo><email>p005-email-1@de.de</email><email>p005-email-2@de.de</email><url>http://p005-url-1.de</url><url>http://p005-url-2.de</url><address>p005-Address</address><zipCode>p005-Zip code</zipCode><city>p005-City</city><region>p005-Region</region><country>p005-Country</country><telephoneNumber>p005-Telephone-1</telephoneNumber><telephoneNumber>p005-Telephone-2</telephoneNumber><faxNumber>p005-Fax-1</faxNumber><faxNumber>p005-Fax-2</faxNumber></communicationInfo><position>p005-Position</position><affiliation><organizationName lang="de">o005-name-2</organizationName><organizationName lang="en">o005-name-1</organizationName><organizationShortName lang="de">o005-short-2</organizationShortName><organizationShortName lang="en">o005-short-1</organizationShortName><departmentName lang="de">o005-Department-2</departmentName><departmentName lang="en">o005-Department-1</departmentName><communicationInfo><email>o005-email-1@de.de</email><email>o005-email-3@de.de</email><url>http://o005-url-1.de</url><url>http://o005-url-2.de</url><address>o005-Address</address><zipCode>o005-zip</zipCode><city>o005-City</city><region>o005-Region</region><country>o005-Country</country><telephoneNumber>o005-Telephone-1</telephoneNumber><telephoneNumber>o005-Telephone-2</telephoneNumber><faxNumber>o005-Fax-1</faxNumber><faxNumber>o005-Fax-2</faxNumber></communicationInfo></affiliation></personInfo></licensor><licensor><organizationInfo><organizationName lang="de">org002-name-2</organizationName><organizationName lang="en">org002-name-1</organizationName><organizationShortName lang="de">org002-short-2</organizationShortName><organizationShortName lang="en">org002-short-1</organizationShortName><departmentName lang="de">org002-Department-2</departmentName><departmentName lang="en">org002-Department-1</departmentName><communicationInfo><email>org002-email-1@de.de</email><email>org002-email-2@de.de</email><url>http://org002-url-1.de</url><url>http://org002-url-2.de</url><address>org002-Address</address><zipCode>org002-zip</zipCode><city>org002-City</city><region>org002-Region</region><country>org002-Country</country><telephoneNumber>org002-Telephone-1</telephoneNumber><telephoneNumber>org002-Telephone-2</telephoneNumber><faxNumber>org002-Fax-1</faxNumber><faxNumber>org002-Fax-2</faxNumber></communicationInfo></organizationInfo></licensor><distributionRightsHolder><personInfo><surname lang="en">p006-Surname-1</surname><givenName lang="en">p006-Given name-1</givenName><sex>female</sex><communicationInfo><email>p006-email-1@de.de</email><email>p006-email-2@de.de</email><url>http://p006-url-1.de</url><url>http://p006-url-2.de</url><address>p006-Address</address><zipCode>p006-Zip code</zipCode><city>p006-City</city><region>p006-Region</region><country>p006-Country</country><telephoneNumber>p006-Telephone-1</telephoneNumber><telephoneNumber>p006-Telephone-2</telephoneNumber><faxNumber>p006-Fax-1</faxNumber><faxNumber>p006-Fax-2</faxNumber></communicationInfo><position>p006-Position</position><affiliation><organizationName lang="de">o006-name-2</organizationName><organizationName lang="en">o006-name-1</organizationName><organizationShortName lang="de">o006-short-2</organizationShortName><organizationShortName lang="en">o006-short-1</organizationShortName><departmentName lang="de">o006-Department-2</departmentName><departmentName lang="en">o006-Department-1</departmentName><communicationInfo><email>o006-email-1@de.de</email><email>o006-email-3@de.de</email><url>http://o006-url-1.de</url><url>http://o006-url-2.de</url><address>o006-Address</address><zipCode>o006-zip</zipCode><city>o006-City</city><region>o006-Region</region><country>o006-Country</country><telephoneNumber>o006-Telephone-1</telephoneNumber><telephoneNumber>o006-Telephone-2</telephoneNumber><faxNumber>o006-Fax-1</faxNumber><faxNumber>o006-Fax-2</faxNumber></communicationInfo></affiliation></personInfo></distributionRightsHolder><distributionRightsHolder><organizationInfo><organizationName lang="de">org003-name-2</organizationName><organizationName lang="en">org003-name-1</organizationName><organizationShortName lang="de">org003-short-2</organizationShortName><organizationShortName lang="en">org003-short-1</organizationShortName><departmentName lang="de">org003-Department-2</departmentName><departmentName lang="en">org003-Department-1</departmentName><communicationInfo><email>org003-email-1@de.de</email><email>org003-email-2@de.de</email><url>http://org003-url-1.de</url><url>http://org003-url-2.de</url><address>org003-Address</address><zipCode>org003-zip</zipCode><city>org003-City</city><region>org003-Region</region><country>org003-Country</country><telephoneNumber>org003-Telephone-1</telephoneNumber><telephoneNumber>org003-Telephone-2</telephoneNumber><faxNumber>org003-Fax-1</faxNumber><faxNumber>org003-Fax-2</faxNumber></communicationInfo></organizationInfo></distributionRightsHolder><userNature>academic</userNature><membershipInfo><member>true</member><membershipInstitution>ELRA</membershipInstitution><membershipInstitution>LDC</membershipInstitution></membershipInfo></licenceInfo><licenceInfo><licence>CC-BY-NC-ND</licence><licence>CC-BY-NC-SA</licence><restrictionsOfUse>redeposit</restrictionsOfUse><restrictionsOfUse>shareAlike</restrictionsOfUse><distributionAccessMedium>paperCopy</distributionAccessMedium><distributionAccessMedium>webExecutable</distributionAccessMedium><downloadLocation>http://006-url.test.de</downloadLocation><executionLocation>http://007-url.test.de</executionLocation><fee>res-fee-2</fee><attributionText lang="de">res-attr-4</attributionText><attributionText lang="en">res-attr-3</attributionText><licensor><personInfo><surname lang="en">p007-Surname-1</surname><givenName lang="en">p007-Given name-1</givenName><sex>female</sex><communicationInfo><email>p007-email-1@de.de</email><email>p007-email-2@de.de</email><url>http://p007-url-1.de</url><url>http://p007-url-2.de</url><address>p007-Address</address><zipCode>p007-Zip code</zipCode><city>p007-City</city><region>p007-Region</region><country>p007-Country</country><telephoneNumber>p007-Telephone-1</telephoneNumber><telephoneNumber>p007-Telephone-2</telephoneNumber><faxNumber>p007-Fax-1</faxNumber><faxNumber>p007-Fax-2</faxNumber></communicationInfo><position>p007-Position</position><affiliation><organizationName lang="de">o007-name-2</organizationName><organizationName lang="en">o007-name-1</organizationName><organizationShortName lang="de">o007-short-2</organizationShortName><organizationShortName lang="en">o007-short-1</organizationShortName><departmentName lang="de">o007-Department-2</departmentName><departmentName lang="en">o007-Department-1</departmentName><communicationInfo><email>o007-email-1@de.de</email><email>o007-email-3@de.de</email><url>http://o007-url-1.de</url><url>http://o007-url-2.de</url><address>o007-Address</address><zipCode>o007-zip</zipCode><city>o007-City</city><region>o007-Region</region><country>o007-Country</country><telephoneNumber>o007-Telephone-1</telephoneNumber><telephoneNumber>o007-Telephone-2</telephoneNumber><faxNumber>o007-Fax-1</faxNumber><faxNumber>o007-Fax-2</faxNumber></communicationInfo></affiliation></personInfo></licensor><licensor><organizationInfo><organizationName lang="de">org003-name-2</organizationName><organizationName lang="en">org003-name-1</organizationName><organizationShortName lang="de">org003-short-2</organizationShortName><organizationShortName lang="en">org003-short-1</organizationShortName><departmentName lang="de">org003-Department-2</departmentName><departmentName lang="en">org003-Department-1</departmentName><communicationInfo><email>org003-email-1@de.de</email><email>org003-email-2@de.de</email><url>http://org003-url-1.de</url><url>http://org003-url-2.de</url><address>org003-Address</address><zipCode>org003-zip</zipCode><city>org003-City</city><region>org003-Region</region><country>org003-Country</country><telephoneNumber>org003-Telephone-1</telephoneNumber><telephoneNumber>org003-Telephone-2</telephoneNumber><faxNumber>org003-Fax-1</faxNumber><faxNumber>org003-Fax-2</faxNumber></communicationInfo></organizationInfo></licensor><distributionRightsHolder><personInfo><surname lang="en">p008-Surname-1</surname><givenName lang="en">p008-Given name-1</givenName><sex>female</sex><communicationInfo><email>p008-email-1@de.de</email><email>p008-email-2@de.de</email><url>http://p008-url-1.de</url><url>http://p008-url-2.de</url><address>p008-Address</address><zipCode>p008-Zip code</zipCode><city>p008-City</city><region>p008-Region</region><country>p008-Country</country><telephoneNumber>p008-Telephone-1</telephoneNumber><telephoneNumber>p008-Telephone-2</telephoneNumber><faxNumber>p008-Fax-1</faxNumber><faxNumber>p008-Fax-2</faxNumber></communicationInfo><position>p008-Position</position><affiliation><organizationName lang="de">o008-name-2</organizationName><organizationName lang="en">o008-name-1</organizationName><organizationShortName lang="de">o008-short-2</organizationShortName><organizationShortName lang="en">o008-short-1</organizationShortName><departmentName lang="de">o008-Department-2</departmentName><departmentName lang="en">o008-Department-1</departmentName><communicationInfo><email>o008-email-1@de.de</email><email>o008-email-3@de.de</email><url>http://o008-url-1.de</url><url>http://o008-url-2.de</url><address>o008-Address</address><zipCode>o008-zip</zipCode><city>o008-City</city><region>o008-Region</region><country>o008-Country</country><telephoneNumber>o008-Telephone-1</telephoneNumber><telephoneNumber>o008-Telephone-2</telephoneNumber><faxNumber>o008-Fax-1</faxNumber><faxNumber>o008-Fax-2</faxNumber></communicationInfo></affiliation></personInfo></distributionRightsHolder><distributionRightsHolder><organizationInfo><organizationName lang="de">org004-name-2</organizationName><organizationName lang="en">org004-name-1</organizationName><organizationShortName lang="de">org004-short-2</organizationShortName><organizationShortName lang="en">org004-short-1</organizationShortName><departmentName lang="de">org004-Department-2</departmentName><departmentName lang="en">org004-Department-1</departmentName><communicationInfo><email>org004-email-1@de.de</email><email>org004-email-2@de.de</email><url>http://org004-url-1.de</url><url>http://org004-url-2.de</url><address>org004-Address</address><zipCode>org004-zip</zipCode><city>org004-City</city><region>org004-Region</region><country>org004-Country</country><telephoneNumber>org004-Telephone-1</telephoneNumber><telephoneNumber>org004-Telephone-2</telephoneNumber><faxNumber>org004-Fax-1</faxNumber><faxNumber>org004-Fax-2</faxNumber></communicationInfo></organizationInfo></distributionRightsHolder><userNature>commercial</userNature><membershipInfo><member>false</member><membershipInstitution>TST-CENTRALE</membershipInstitution></membershipInfo></licenceInfo><iprHolder><personInfo><surname lang="en">p004-Surname-1</surname><givenName lang="en">p004-Given name-1</givenName><sex>female</sex><communicationInfo><email>p004-email-1@de.de</email><email>p004-email-2@de.de</email><url>http://p004-url-1.de</url><url>http://p004-url-2.de</url><address>p004-Address</address><zipCode>p004-Zip code</zipCode><city>p004-City</city><region>p004-Region</region><country>p004-Country</country><telephoneNumber>p004-Telephone-1</telephoneNumber><telephoneNumber>p004-Telephone-2</telephoneNumber><faxNumber>p004-Fax-1</faxNumber><faxNumber>p004-Fax-2</faxNumber></communicationInfo><position>p004-Position</position><affiliation><organizationName lang="de">o004-name-2</organizationName><organizationName lang="en">o004-name-1</organizationName><organizationShortName lang="de">o004-short-2</organizationShortName><organizationShortName lang="en">o004-short-1</organizationShortName><departmentName lang="de">o004-Department-2</departmentName><departmentName lang="en">o004-Department-1</departmentName><communicationInfo><email>o004-email-1@de.de</email><email>o004-email-3@de.de</email><url>http://o004-url-1.de</url><url>http://o004-url-2.de</url><address>o004-Address</address><zipCode>o004-zip</zipCode><city>o004-City</city><region>o004-Region</region><country>o004-Country</country><telephoneNumber>o004-Telephone-1</telephoneNumber><telephoneNumber>o004-Telephone-2</telephoneNumber><faxNumber>o004-Fax-1</faxNumber><faxNumber>o004-Fax-2</faxNumber></communicationInfo></affiliation></personInfo></iprHolder><iprHolder><organizationInfo><organizationName lang="de">org000-name-2</organizationName><organizationName lang="en">org000-name-1</organizationName><organizationShortName lang="de">org000-short-2</organizationShortName><organizationShortName lang="en">org000-short-1</organizationShortName><departmentName lang="de">org000-Department-2</departmentName><departmentName lang="en">org000-Department-1</departmentName><communicationInfo><email>org000-email-1@de.de</email><email>org000-email-2@de.de</email><url>http://org000-url-1.de</url><url>http://org000-url-2.de</url><address>org000-Address</address><zipCode>org000-zip</zipCode><city>org000-City</city><region>org000-Region</region><country>org000-Country</country><telephoneNumber>org000-Telephone-1</telephoneNumber><telephoneNumber>org000-Telephone-2</telephoneNumber><faxNumber>org000-Fax-1</faxNumber><faxNumber>org000-Fax-2</faxNumber></communicationInfo></organizationInfo></iprHolder><availabilityEndDate>2000-09-27</availabilityEndDate><availabilityStartDate>2000-09-27</availabilityStartDate></distributionInfo><contactPerson><surname lang="en">p000-Surname-1</surname><givenName lang="en">p000-Given name-1</givenName><sex>female</sex><communicationInfo><email>p000-email-1@de.de</email><email>p000-email-2@de.de</email><url>http://p000-url-1.de</url><url>http://p000-url-2.de</url><address>p000-Address</address><zipCode>p000-Zip code</zipCode><city>p000-City</city><region>p000-Region</region><country>p000-Country</country><telephoneNumber>p000-Telephone-1</telephoneNumber><telephoneNumber>p000-Telephone-2</telephoneNumber><faxNumber>p000-Fax-1</faxNumber><faxNumber>p000-Fax-2</faxNumber></communicationInfo><position>p000-Position</position><affiliation><organizationName lang="de">o000-name-2</organizationName><organizationName lang="en">o000-name-1</organizationName><organizationShortName lang="de">o000-short-2</organizationShortName><organizationShortName lang="en">o000-short-1</organizationShortName><departmentName lang="de">o000-Department-2</departmentName><departmentName lang="en">o000-Department-1</departmentName><communicationInfo><email>o000-email-1@de.de</email><email>o000-email-3@de.de</email><url>http://o000-url-1.de</url><url>http://o000-url-2.de</url><address>o000-Address</address><zipCode>o000-zip</zipCode><city>o000-City</city><region>o000-Region</region><country>o000-Country</country><telephoneNumber>o000-Telephone-1</telephoneNumber><telephoneNumber>o000-Telephone-2</telephoneNumber><faxNumber>o000-Fax-1</faxNumber><faxNumber>o000-Fax-2</faxNumber></communicationInfo></affiliation></contactPerson><contactPerson><surname lang="en">p001-Surname-1</surname><givenName lang="en">p001-Given name-1</givenName><sex>female</sex><communicationInfo><email>p001-email-1@de.de</email><email>p001-email-2@de.de</email><url>http://p001-url-1.de</url><url>http://p001-url-2.de</url><address>p001-Address</address><zipCode>p001-Zip code</zipCode><city>p001-City</city><region>p001-Region</region><country>p001-Country</country><telephoneNumber>p001-Telephone-1</telephoneNumber><telephoneNumber>p001-Telephone-2</telephoneNumber><faxNumber>p001-Fax-1</faxNumber><faxNumber>p001-Fax-2</faxNumber></communicationInfo><position>p001-Position</position><affiliation><organizationName lang="de">o001-name-2</organizationName><organizationName lang="en">o001-name-1</organizationName><organizationShortName lang="de">o001-short-2</organizationShortName><organizationShortName lang="en">o001-short-1</organizationShortName><departmentName lang="de">o001-Department-2</departmentName><departmentName lang="en">o001-Department-1</departmentName><communicationInfo><email>o001-email-1@de.de</email><email>o001-email-3@de.de</email><url>http://o001-url-1.de</url><url>http://o001-url-2.de</url><address>o001-Address</address><zipCode>o001-zip</zipCode><city>o001-City</city><region>o001-Region</region><country>o001-Country</country><telephoneNumber>o001-Telephone-1</telephoneNumber><telephoneNumber>o001-Telephone-2</telephoneNumber><faxNumber>o001-Fax-1</faxNumber><faxNumber>o001-Fax-2</faxNumber></communicationInfo></affiliation></contactPerson><metadataInfo><metadataCreationDate>2012-09-27</metadataCreationDate><metadataCreator><surname lang="en">p002-Surname-1</surname><givenName lang="en">p002-Given name-1</givenName><sex>female</sex><communicationInfo><email>p002-email-1@de.de</email><email>p002-email-2@de.de</email><url>http://p002-url-1.de</url><url>http://p002-url-2.de</url><address>p002-Address</address><zipCode>p002-Zip code</zipCode><city>p002-City</city><region>p002-Region</region><country>p002-Country</country><telephoneNumber>p002-Telephone-1</telephoneNumber><telephoneNumber>p002-Telephone-2</telephoneNumber><faxNumber>p002-Fax-1</faxNumber><faxNumber>p002-Fax-2</faxNumber></communicationInfo><position>p002-Position</position><affiliation><organizationName lang="de">o002-name-2</organizationName><organizationName lang="en">o002-name-1</organizationName><organizationShortName lang="de">o002-short-2</organizationShortName><organizationShortName lang="en">o002-short-1</organizationShortName><departmentName lang="de">o002-Department-2</departmentName><departmentName lang="en">o002-Department-1</departmentName><communicationInfo><email>o002-email-1@de.de</email><email>o002-email-3@de.de</email><url>http://o002-url-1.de</url><url>http://o002-url-2.de</url><address>o002-Address</address><zipCode>o002-zip</zipCode><city>o002-City</city><region>o002-Region</region><country>o002-Country</country><telephoneNumber>o002-Telephone-1</telephoneNumber><telephoneNumber>o002-Telephone-2</telephoneNumber><faxNumber>o002-Fax-1</faxNumber><faxNumber>o002-Fax-2</faxNumber></communicationInfo></affiliation></metadataCreator><metadataCreator><surname lang="en">p003-Surname-1</surname><givenName lang="en">p003-Given name-1</givenName><sex>female</sex><communicationInfo><email>p003-email-1@de.de</email><email>p003-email-2@de.de</email><url>http://p003-url-1.de</url><url>http://p003-url-2.de</url><address>p003-Address</address><zipCode>p003-Zip code</zipCode><city>p003-City</city><region>p003-Region</region><country>p003-Country</country><telephoneNumber>p003-Telephone-1</telephoneNumber><telephoneNumber>p003-Telephone-2</telephoneNumber><faxNumber>p003-Fax-1</faxNumber><faxNumber>p003-Fax-2</faxNumber></communicationInfo><position>p003-Position</position><affiliation><organizationName lang="de">o003-name-2</organizationName><organizationName lang="en">o003-name-1</organizationName><organizationShortName lang="de">o003-short-2</organizationShortName><organizationShortName lang="en">o003-short-1</organizationShortName><departmentName lang="de">o003-Department-2</departmentName><departmentName lang="en">o003-Department-1</departmentName><communicationInfo><email>o003-email-1@de.de</email><email>o003-email-3@de.de</email><url>http://o003-url-1.de</url><url>http://o003-url-2.de</url><address>o003-Address</address><zipCode>o003-zip</zipCode><city>o003-City</city><region>o003-Region</region><country>o003-Country</country><telephoneNumber>o003-Telephone-1</telephoneNumber><telephoneNumber>o003-Telephone-2</telephoneNumber><faxNumber>o003-Fax-1</faxNumber><faxNumber>o003-Fax-2</faxNumber></communicationInfo></affiliation></metadataCreator><source>res-source</source><originalMetadataSchema>res-org-metadata-schema</originalMetadataSchema><originalMetadataLink>http://023-url.test.de</originalMetadataLink><metadataLanguageName>German</metadataLanguageName><metadataLanguageName>English</metadataLanguageName><metadataLanguageId>de</metadataLanguageId><metadataLanguageId>en</metadataLanguageId><metadataLastDateUpdated>2012-09-27</metadataLastDateUpdated><revision>res-revision</revision></metadataInfo><versionInfo><version>res-version</version><revision>res-rev</revision><lastDateUpdated>2001-09-27</lastDateUpdated><updateFrequency>upd-freq-1</updateFrequency></versionInfo><validationInfo><validated>true</validated><validationType>content</validationType><validationMode>automatic</validationMode><validationModeDetails>val-mode-details-1</validationModeDetails><validationExtent>partial</validationExtent><validationExtentDetails>val-ext-details</validationExtentDetails><sizePerValidation><size>11</size><sizeUnit>5-grams</sizeUnit></sizePerValidation><validationReport><documentInfo><documentType>article</documentType><title lang="de">doc000-title-2</title><title lang="en">doc000-title-1</title><author>doc000-author-1</author><author>doc000-author-2</author><editor>doc000-editor-1</editor><editor>doc000-editor-2</editor><year>2000</year><publisher>doc000-pub-1</publisher><publisher>doc000-pub-2</publisher><bookTitle>doc000-Book title</bookTitle><journal>doc000-journal</journal><volume>doc000-volume</volume><series>doc000-series</series><pages>doc000-pages</pages><edition>doc000-edition</edition><conference>doc000-conference</conference><doi>doc000-doi</doi><url>http://doc000-url.de</url><ISSN>doc000-issn</ISSN><ISBN>doc000-isbn</ISBN><keywords>doc000-key-1</keywords><keywords>doc000-key-2</keywords><documentLanguageName>English</documentLanguageName><documentLanguageId>en</documentLanguageId></documentInfo></validationReport><validationTool><targetResourceNameURI>http://008-url.test.de</targetResourceNameURI></validationTool><validator><personInfo><surname lang="en">p009-Surname-1</surname><givenName lang="en">p009-Given name-1</givenName><sex>female</sex><communicationInfo><email>p009-email-1@de.de</email><email>p009-email-2@de.de</email><url>http://p009-url-1.de</url><url>http://p009-url-2.de</url><address>p009-Address</address><zipCode>p009-Zip code</zipCode><city>p009-City</city><region>p009-Region</region><country>p009-Country</country><telephoneNumber>p009-Telephone-1</telephoneNumber><telephoneNumber>p009-Telephone-2</telephoneNumber><faxNumber>p009-Fax-1</faxNumber><faxNumber>p009-Fax-2</faxNumber></communicationInfo><position>p009-Position</position><affiliation><organizationName lang="de">o009-name-2</organizationName><organizationName lang="en">o009-name-1</organizationName><organizationShortName lang="de">o009-short-2</organizationShortName><organizationShortName lang="en">o009-short-1</organizationShortName><departmentName lang="de">o009-Department-2</departmentName><departmentName lang="en">o009-Department-1</departmentName><communicationInfo><email>o009-email-1@de.de</email><email>o009-email-3@de.de</email><url>http://o009-url-1.de</url><url>http://o009-url-2.de</url><address>o009-Address</address><zipCode>o009-zip</zipCode><city>o009-City</city><region>o009-Region</region><country>o009-Country</country><telephoneNumber>o009-Telephone-1</telephoneNumber><telephoneNumber>o009-Telephone-2</telephoneNumber><faxNumber>o009-Fax-1</faxNumber><faxNumber>o009-Fax-2</faxNumber></communicationInfo></affiliation></personInfo></validator><validator><organizationInfo><organizationName lang="de">org005-name-2</organizationName><organizationName lang="en">org005-name-1</organizationName><organizationShortName lang="de">org005-short-2</organizationShortName><organizationShortName lang="en">org005-short-1</organizationShortName><departmentName lang="de">org005-Department-2</departmentName><departmentName lang="en">org005-Department-1</departmentName><communicationInfo><email>org005-email-1@de.de</email><email>org005-email-2@de.de</email><url>http://org005-url-1.de</url><url>http://org005-url-2.de</url><address>org005-Address</address><zipCode>org005-zip</zipCode><city>org005-City</city><region>org005-Region</region><country>org005-Country</country><telephoneNumber>org005-Telephone-1</telephoneNumber><telephoneNumber>org005-Telephone-2</telephoneNumber><faxNumber>org005-Fax-1</faxNumber><faxNumber>org005-Fax-2</faxNumber></communicationInfo></organizationInfo></validator></validationInfo><validationInfo><validated>true</validated><validationType>formal</validationType><validationMode>automatic</validationMode><validationModeDetails>val-mode-det-2</validationModeDetails><validationExtent>partial</validationExtent><validationExtentDetails>val-ext-details-2</validationExtentDetails><sizePerValidation><size>22</size><sizeUnit>articles</sizeUnit></sizePerValidation><validationReport><documentInfo><documentType>article</documentType><title lang="de">doc001-title-2</title><title lang="en">doc001-title-1</title><author>doc001-author-1</author><author>doc001-author-2</author><editor>doc001-editor-1</editor><editor>doc001-editor-2</editor><year>2000</year><publisher>doc001-pub-1</publisher><publisher>doc001-pub-2</publisher><bookTitle>doc001-Book title</bookTitle><journal>doc001-journal</journal><volume>doc001-volume</volume><series>doc001-series</series><pages>doc001-pages</pages><edition>doc001-edition</edition><conference>doc001-conference</conference><doi>doc001-doi</doi><url>http://doc001-url.de</url><ISSN>doc001-issn</ISSN><ISBN>doc001-isbn</ISBN><keywords>doc001-key-1</keywords><keywords>doc001-key-2</keywords><documentLanguageName>English</documentLanguageName><documentLanguageId>en</documentLanguageId></documentInfo></validationReport><validationTool><targetResourceNameURI>http://009-url.test.de</targetResourceNameURI></validationTool><validator><personInfo><surname lang="en">p010-Surname-1</surname><givenName lang="en">p010-Given name-1</givenName><sex>female</sex><communicationInfo><email>p010-email-1@de.de</email><email>p010-email-2@de.de</email><url>http://p010-url-1.de</url><url>http://p010-url-2.de</url><address>p010-Address</address><zipCode>p010-Zip code</zipCode><city>p010-City</city><region>p010-Region</region><country>p010-Country</country><telephoneNumber>p010-Telephone-1</telephoneNumber><telephoneNumber>p010-Telephone-2</telephoneNumber><faxNumber>p010-Fax-1</faxNumber><faxNumber>p010-Fax-2</faxNumber></communicationInfo><position>p010-Position</position><affiliation><organizationName lang="de">o010-name-2</organizationName><organizationName lang="en">o010-name-1</organizationName><organizationShortName lang="de">o010-short-2</organizationShortName><organizationShortName lang="en">o010-short-1</organizationShortName><departmentName lang="de">o010-Department-2</departmentName><departmentName lang="en">o010-Department-1</departmentName><communicationInfo><email>o010-email-1@de.de</email><email>o010-email-3@de.de</email><url>http://o010-url-1.de</url><url>http://o010-url-2.de</url><address>o010-Address</address><zipCode>o010-zip</zipCode><city>o010-City</city><region>o010-Region</region><country>o010-Country</country><telephoneNumber>o010-Telephone-1</telephoneNumber><telephoneNumber>o010-Telephone-2</telephoneNumber><faxNumber>o010-Fax-1</faxNumber><faxNumber>o010-Fax-2</faxNumber></communicationInfo></affiliation></personInfo></validator><validator><organizationInfo><organizationName lang="de">org005-name-2</organizationName><organizationName lang="en">org005-name-1</organizationName><organizationShortName lang="de">org005-short-2</organizationShortName><organizationShortName lang="en">org005-short-1</organizationShortName><departmentName lang="de">org005-Department-2</departmentName><departmentName lang="en">org005-Department-1</departmentName><communicationInfo><email>org005-email-1@de.de</email><email>org005-email-2@de.de</email><url>http://org005-url-1.de</url><url>http://org005-url-2.de</url><address>org005-Address</address><zipCode>org005-zip</zipCode><city>org005-City</city><region>org005-Region</region><country>org005-Country</country><telephoneNumber>org005-Telephone-1</telephoneNumber><telephoneNumber>org005-Telephone-2</telephoneNumber><faxNumber>org005-Fax-1</faxNumber><faxNumber>org005-Fax-2</faxNumber></communicationInfo></organizationInfo></validator></validationInfo><usageInfo><accessTool><targetResourceNameURI>http://010-url.test.de</targetResourceNameURI></accessTool><accessTool><targetResourceNameURI>http://011-url.test.de</targetResourceNameURI></accessTool><resourceAssociatedWith><targetResourceNameURI>http://012-url.test.de</targetResourceNameURI></resourceAssociatedWith><resourceAssociatedWith><targetResourceNameURI>http://013-url.test.de</targetResourceNameURI></resourceAssociatedWith><foreseenUseInfo><foreseenUse>humanUse</foreseenUse><useNLPSpecific>annotation</useNLPSpecific><useNLPSpecific>avatarSynthesis</useNLPSpecific></foreseenUseInfo><foreseenUseInfo><foreseenUse>nlpApplications</foreseenUse><useNLPSpecific>faceRecognition</useNLPSpecific><useNLPSpecific>faceVerification</useNLPSpecific></foreseenUseInfo><actualUseInfo><actualUse>humanUse</actualUse><useNLPSpecific>discourseAnalysis</useNLPSpecific><useNLPSpecific>entityMentionRecognition</useNLPSpecific><usageReport><documentInfo><documentType>article</documentType><title lang="de">doc002-title-2</title><title lang="en">doc002-title-1</title><author>doc002-author-1</author><author>doc002-author-2</author><editor>doc002-editor-1</editor><editor>doc002-editor-2</editor><year>2000</year><publisher>doc002-pub-1</publisher><publisher>doc002-pub-2</publisher><bookTitle>doc002-Book title</bookTitle><journal>doc002-journal</journal><volume>doc002-volume</volume><series>doc002-series</series><pages>doc002-pages</pages><edition>doc002-edition</edition><conference>doc002-conference</conference><doi>doc002-doi</doi><url>http://doc002-url.de</url><ISSN>doc002-issn</ISSN><ISBN>doc002-isbn</ISBN><keywords>doc002-key-1</keywords><keywords>doc002-key-2</keywords><documentLanguageName>English</documentLanguageName><documentLanguageId>en</documentLanguageId></documentInfo></usageReport><derivedResource><targetResourceNameURI>http://014-url.test.de</targetResourceNameURI></derivedResource><derivedResource><targetResourceNameURI>http://015-url.test.de</targetResourceNameURI></derivedResource><usageProject><projectName lang="de">proj000-name-2</projectName><projectName lang="en">proj000-name-1</projectName><projectShortName lang="de">proj000-short-2</projectShortName><projectShortName lang="en">proj000-short-1</projectShortName><projectID>proj000-id</projectID><url>http://proj000-url-1.de</url><url>http://proj000-url-2.de</url><fundingType>euFunds</fundingType><fundingType>nationalFunds</fundingType><funder>proj000-Funder-1</funder><funder>proj000-Funder-2</funder><fundingCountry>proj000-Funding country-1</fundingCountry><fundingCountry>proj000-Funding country-2</fundingCountry><projectStartDate>2001-09-02</projectStartDate><projectEndDate>2001-09-27</projectEndDate></usageProject><usageProject><projectName lang="de">proj001-name-2</projectName><projectName lang="en">proj001-name-1</projectName><projectShortName lang="de">proj001-short-2</projectShortName><projectShortName lang="en">proj001-short-1</projectShortName><projectID>proj001-id</projectID><url>http://proj001-url-1.de</url><url>http://proj001-url-2.de</url><fundingType>euFunds</fundingType><fundingType>nationalFunds</fundingType><funder>proj001-Funder-1</funder><funder>proj001-Funder-2</funder><fundingCountry>proj001-Funding country-1</fundingCountry><fundingCountry>proj001-Funding country-2</fundingCountry><projectStartDate>2001-09-02</projectStartDate><projectEndDate>2001-09-27</projectEndDate></usageProject><actualUseDetails>act-use-details-1</actualUseDetails></actualUseInfo><actualUseInfo><actualUse>nlpApplications</actualUse><useNLPSpecific>entityMentionRecognition</useNLPSpecific><useNLPSpecific>informationExtraction</useNLPSpecific><usageReport><documentInfo><documentType>article</documentType><title lang="de">doc003-title-2</title><title lang="en">doc003-title-1</title><author>doc003-author-1</author><author>doc003-author-2</author><editor>doc003-editor-1</editor><editor>doc003-editor-2</editor><year>2000</year><publisher>doc003-pub-1</publisher><publisher>doc003-pub-2</publisher><bookTitle>doc003-Book title</bookTitle><journal>doc003-journal</journal><volume>doc003-volume</volume><series>doc003-series</series><pages>doc003-pages</pages><edition>doc003-edition</edition><conference>doc003-conference</conference><doi>doc003-doi</doi><url>http://doc003-url.de</url><ISSN>doc003-issn</ISSN><ISBN>doc003-isbn</ISBN><keywords>doc003-key-1</keywords><keywords>doc003-key-2</keywords><documentLanguageName>English</documentLanguageName><documentLanguageId>en</documentLanguageId></documentInfo></usageReport><derivedResource><targetResourceNameURI>http://017-url.test.de</targetResourceNameURI></derivedResource><derivedResource><targetResourceNameURI>http://018-url.test.de</targetResourceNameURI></derivedResource><usageProject><projectName lang="de">proj002-name-2</projectName><projectName lang="en">proj002-name-1</projectName><projectShortName lang="de">proj002-short-2</projectShortName><projectShortName lang="en">proj002-short-1</projectShortName><projectID>proj002-id</projectID><url>http://proj002-url-1.de</url><url>http://proj002-url-2.de</url><fundingType>euFunds</fundingType><fundingType>nationalFunds</fundingType><funder>proj002-Funder-1</funder><funder>proj002-Funder-2</funder><fundingCountry>proj002-Funding country-1</fundingCountry><fundingCountry>proj002-Funding country-2</fundingCountry><projectStartDate>2001-09-02</projectStartDate><projectEndDate>2001-09-27</projectEndDate></usageProject><actualUseDetails>act-use-details-2</actualUseDetails></actualUseInfo></usageInfo><resourceDocumentationInfo><documentation><documentInfo><documentType>article</documentType><title lang="de">doc004-title-2</title><title lang="en">doc004-title-1</title><author>doc004-author-1</author><author>doc004-author-2</author><editor>doc004-editor-1</editor><editor>doc004-editor-2</editor><year>2000</year><publisher>doc004-pub-1</publisher><publisher>doc004-pub-2</publisher><bookTitle>doc004-Book title</bookTitle><journal>doc004-journal</journal><volume>doc004-volume</volume><series>doc004-series</series><pages>doc004-pages</pages><edition>doc004-edition</edition><conference>doc004-conference</conference><doi>doc004-doi</doi><url>http://doc004-url.de</url><ISSN>doc004-issn</ISSN><ISBN>doc004-isbn</ISBN><keywords>doc004-key-1</keywords><keywords>doc004-key-2</keywords><documentLanguageName>English</documentLanguageName><documentLanguageId>en</documentLanguageId></documentInfo></documentation><samplesLocation>http://019-url.test.de</samplesLocation><samplesLocation>http://020-url.test.de</samplesLocation><toolDocumentationType>helpFunctions</toolDocumentationType><toolDocumentationType>manual</toolDocumentationType></resourceDocumentationInfo><resourceCreationInfo><resourceCreator><personInfo><surname lang="en">p011-Surname-1</surname><givenName lang="en">p011-Given name-1</givenName><sex>female</sex><communicationInfo><email>p011-email-1@de.de</email><email>p011-email-2@de.de</email><url>http://p011-url-1.de</url><url>http://p011-url-2.de</url><address>p011-Address</address><zipCode>p011-Zip code</zipCode><city>p011-City</city><region>p011-Region</region><country>p011-Country</country><telephoneNumber>p011-Telephone-1</telephoneNumber><telephoneNumber>p011-Telephone-2</telephoneNumber><faxNumber>p011-Fax-1</faxNumber><faxNumber>p011-Fax-2</faxNumber></communicationInfo><position>p011-Position</position><affiliation><organizationName lang="de">o011-name-2</organizationName><organizationName lang="en">o011-name-1</organizationName><organizationShortName lang="de">o011-short-2</organizationShortName><organizationShortName lang="en">o011-short-1</organizationShortName><departmentName lang="de">o011-Department-2</departmentName><departmentName lang="en">o011-Department-1</departmentName><communicationInfo><email>o011-email-1@de.de</email><email>o011-email-3@de.de</email><url>http://o011-url-1.de</url><url>http://o011-url-2.de</url><address>o011-Address</address><zipCode>o011-zip</zipCode><city>o011-City</city><region>o011-Region</region><country>o011-Country</country><telephoneNumber>o011-Telephone-1</telephoneNumber><telephoneNumber>o011-Telephone-2</telephoneNumber><faxNumber>o011-Fax-1</faxNumber><faxNumber>o011-Fax-2</faxNumber></communicationInfo></affiliation></personInfo></resourceCreator><fundingProject><projectName lang="de">proj002-name-2</projectName><projectName lang="en">proj002-name-1</projectName><projectShortName lang="de">proj002-short-2</projectShortName><projectShortName lang="en">proj002-short-1</projectShortName><projectID>proj002-id</projectID><url>http://proj002-url-1.de</url><url>http://proj002-url-2.de</url><fundingType>euFunds</fundingType><fundingType>nationalFunds</fundingType><funder>proj002-Funder-1</funder><funder>proj002-Funder-2</funder><fundingCountry>proj002-Funding country-1</fundingCountry><fundingCountry>proj002-Funding country-2</fundingCountry><projectStartDate>2001-09-02</projectStartDate><projectEndDate>2001-09-27</projectEndDate></fundingProject><fundingProject><projectName lang="de">proj003-name-2</projectName><projectName lang="en">proj003-name-1</projectName><projectShortName lang="de">proj003-short-2</projectShortName><projectShortName lang="en">proj003-short-1</projectShortName><projectID>proj003-id</projectID><url>http://proj003-url-1.de</url><url>http://proj003-url-2.de</url><fundingType>euFunds</fundingType><fundingType>nationalFunds</fundingType><funder>proj003-Funder-1</funder><funder>proj003-Funder-2</funder><fundingCountry>proj003-Funding country-1</fundingCountry><fundingCountry>proj003-Funding country-2</fundingCountry><projectStartDate>2001-09-02</projectStartDate><projectEndDate>2001-09-27</projectEndDate></fundingProject><creationStartDate>2002-09-27</creationStartDate><creationEndDate>2002-09-27</creationEndDate></resourceCreationInfo><relationInfo><relationType>rel-type-1</relationType><relatedResource><targetResourceNameURI>http://022-url.test.de</targetResourceNameURI></relatedResource></relationInfo><relationInfo><relationType>rel-type-2</relationType><relatedResource><targetResourceNameURI>http://024-url.test.de</targetResourceNameURI></relatedResource></relationInfo><resourceComponentType><corpusInfo><resourceType>corpus</resourceType><corpusMediaType><corpusImageInfo><mediaType>image</mediaType><modalityInfo><modalityType>combinationOfModalities</modalityType><modalityType>facialExpression</modalityType><modalityTypeDetails>modtypedetails34456457</modalityTypeDetails><sizePerModality><size>256857867</size><sizeUnit>other</sizeUnit></sizePerModality></modalityInfo><modalityInfo><modalityType>signLanguage</modalityType><modalityType>spokenLanguage</modalityType><modalityTypeDetails>modalitytypedetails9435003</modalityTypeDetails><sizePerModality><size>5743568568</size><sizeUnit>bytes</sizeUnit></sizePerModality></modalityInfo><lingualityInfo><lingualityType>bilingual</lingualityType><multilingualityType>multilingualSingleText</multilingualityType><multilingualityTypeDetails>multilingtypedetails</multilingualityTypeDetails></lingualityInfo><languageInfo><languageId>de</languageId><languageName>German</languageName><languageScript>langscript309450ß</languageScript><sizePerLanguage><size>346445</size><sizeUnit>files</sizeUnit></sizePerLanguage><languageVarietyInfo><languageVarietyType>jargon</languageVarietyType><languageVarietyName>langvarietyname9358000000</languageVarietyName><sizePerLanguageVariety><size>94359803400000</size><sizeUnit>frames</sizeUnit></sizePerLanguageVariety></languageVarietyInfo></languageInfo><languageInfo><languageId>ale</languageId><languageName>Aleut</languageName><languageScript>languagescript</languageScript><sizePerLanguage><size>4568994050000504554</size><sizeUnit>questions</sizeUnit></sizePerLanguage><languageVarietyInfo><languageVarietyType>jargon</languageVarietyType><languageVarietyName>languavarietyname</languageVarietyName><sizePerLanguageVariety><size>9438908</size><sizeUnit>5-grams</sizeUnit></sizePerLanguageVariety></languageVarietyInfo></languageInfo><sizeInfo><size>7575</size><sizeUnit>bigrams</sizeUnit></sizeInfo><sizeInfo><size>457568678</size><sizeUnit>hours</sizeUnit></sizeInfo><imageContentInfo><typeOfImageContent>typeofimagecontent39540046</typeOfImageContent><typeOfImageContent>typeofimagecontetn340ßß05433</typeOfImageContent><textIncludedInImage>none</textIncludedInImage><textIncludedInImage>subtitles</textIncludedInImage><staticElementInfo><typeOfElement>typeofelement349003</typeOfElement><typeOfElement>typeofelement934004</typeOfElement><bodyParts>feet</bodyParts><bodyParts>wholeBody</bodyParts><faceViews>faceviews093404</faceViews><faceViews>faceviews34903044334</faceViews><faceExpressions>faceexpressions34ß005454</faceExpressions><faceExpressions>faceexpression400ß435ß054</faceExpressions><artifactParts>artifactpart439008830443</artifactParts><artifactParts>artifactparts39580030443</artifactParts><landscapeParts>landcapeparts38459043</landscapeParts><landscapeParts>landscapeparts84935034</landscapeParts><personDescription>persondescrio4358080485</personDescription><personDescription>persondescription34950046</personDescription><thingDescription>thingdescript90485609465</thingDescription><thingDescription>thingdescriptions8340534</thingDescription><organizationDescription>organdescription4569909456</organizationDescription><organizationDescription>organdescription34590546</organizationDescription><eventDescription>eventdescriptio45890436</eventDescription><eventDescription>eventdescriptio435980546</eventDescription></staticElementInfo></imageContentInfo><imageFormatInfo><mimeType>mimetype94385034</mimeType><colourSpace>4:2:2</colourSpace><colourSpace>RGB</colourSpace><colourDepth>36243</colourDepth><compressionInfo><compression>false</compression><compressionName>avi</compressionName><compressionName>flac</compressionName><compressionLoss>true</compressionLoss></compressionInfo><resolutionInfo><sizeWidth>934</sizeWidth><sizeHeight>37846</sizeHeight><resolutionStandard>HD.720</resolutionStandard></resolutionInfo><visualModelling>3D</visualModelling><rasterOrVectorGraphics>raster</rasterOrVectorGraphics><quality>veryHigh</quality><sizePerImageFormat><size>4643664643</size><sizeUnit>4-grams</sizeUnit></sizePerImageFormat></imageFormatInfo><imageFormatInfo><mimeType>mimetype983405</mimeType><colourSpace>CMYK</colourSpace><colourSpace>RGB</colourSpace><colourDepth>346</colourDepth><compressionInfo><compression>false</compression><compressionName>avi</compressionName><compressionLoss>false</compressionLoss></compressionInfo><resolutionInfo><sizeWidth>436</sizeWidth><sizeHeight>456</sizeHeight><resolutionStandard>VGA</resolutionStandard></resolutionInfo><visualModelling>2D</visualModelling><rasterOrVectorGraphics>raster</rasterOrVectorGraphics><quality>medium</quality><sizePerImageFormat><size>684697</size><sizeUnit>predicates</sizeUnit></sizePerImageFormat></imageFormatInfo><annotationInfo><annotationType>stemming</annotationType><annotatedElements>discourseMarkers</annotatedElements><annotatedElements>speakerNoise</annotatedElements><annotationStandoff>true</annotationStandoff><segmentationLevel>diphone</segmentationLevel><segmentationLevel>other</segmentationLevel><annotationFormat>annotationformat09430ß54</annotationFormat><tagset>tagset8349043</tagset><tagsetLanguageId>ht</tagsetLanguageId><tagsetLanguageName>Haitian; Haitian Creole</tagsetLanguageName><conformanceToStandardsBestPractices>MAF</conformanceToStandardsBestPractices><conformanceToStandardsBestPractices>TBX</conformanceToStandardsBestPractices><theoreticModel>theoreticmodel4994</theoreticModel><annotationManual><documentInfo><documentType>article</documentType><title lang="de">doc024-title-2</title><title lang="en">doc024-title-1</title><author>doc024-author-1</author><author>doc024-author-2</author><editor>doc024-editor-1</editor><editor>doc024-editor-2</editor><year>2000</year><publisher>doc024-pub-1</publisher><publisher>doc024-pub-2</publisher><bookTitle>doc024-Book title</bookTitle><journal>doc024-journal</journal><volume>doc024-volume</volume><series>doc024-series</series><pages>doc024-pages</pages><edition>doc024-edition</edition><conference>doc024-conference</conference><doi>doc024-doi</doi><url>http://doc024-url.de</url><ISSN>doc024-issn</ISSN><ISBN>doc024-isbn</ISBN><keywords>doc024-key-1</keywords><keywords>doc024-key-2</keywords><documentLanguageName>English</documentLanguageName><documentLanguageId>en</documentLanguageId></documentInfo></annotationManual><annotationManual><documentInfo><documentType>article</documentType><title lang="de">doc025-title-2</title><title lang="en">doc025-title-1</title><author>doc025-author-1</author><author>doc025-author-2</author><editor>doc025-editor-1</editor><editor>doc025-editor-2</editor><year>2000</year><publisher>doc025-pub-1</publisher><publisher>doc025-pub-2</publisher><bookTitle>doc025-Book title</bookTitle><journal>doc025-journal</journal><volume>doc025-volume</volume><series>doc025-series</series><pages>doc025-pages</pages><edition>doc025-edition</edition><conference>doc025-conference</conference><doi>doc025-doi</doi><url>http://doc025-url.de</url><ISSN>doc025-issn</ISSN><ISBN>doc025-isbn</ISBN><keywords>doc025-key-1</keywords><keywords>doc025-key-2</keywords><documentLanguageName>English</documentLanguageName><documentLanguageId>en</documentLanguageId></documentInfo></annotationManual><annotationMode>mixed</annotationMode><annotationModeDetails>annotationmodedetails400403232</annotationModeDetails><annotationTool><targetResourceNameURI>annotatooltargeresoucename84395034</targetResourceNameURI></annotationTool><annotationTool><targetResourceNameURI>targetresorcenameuir943560ß1345</targetResourceNameURI></annotationTool><annotationStartDate>2012-06-12</annotationStartDate><annotationEndDate>2012-08-20</annotationEndDate><sizePerAnnotation><size>64545645</size><sizeUnit>questions</sizeUnit></sizePerAnnotation><interannotatorAgreement>interannotatoragreem49504304</interannotatorAgreement><intraannotatorAgreement>intraannottaor8435609509</intraannotatorAgreement><annotator><personInfo><surname lang="en">p033-Surname-1</surname><givenName lang="en">p033-Given name-1</givenName><sex>female</sex><communicationInfo><email>p033-email-1@de.de</email><email>p033-email-2@de.de</email><url>http://p033-url-1.de</url><url>http://p033-url-2.de</url><address>p033-Address</address><zipCode>p033-Zip code</zipCode><city>p033-City</city><region>p033-Region</region><country>p033-Country</country><telephoneNumber>p033-Telephone-1</telephoneNumber><telephoneNumber>p033-Telephone-2</telephoneNumber><faxNumber>p033-Fax-1</faxNumber><faxNumber>p033-Fax-2</faxNumber></communicationInfo><position>p033-Position</position><affiliation><organizationName lang="de">o033-name-2</organizationName><organizationName lang="en">o033-name-1</organizationName><organizationShortName lang="de">o033-short-2</organizationShortName><organizationShortName lang="en">o033-short-1</organizationShortName><departmentName lang="de">o033-Department-2</departmentName><departmentName lang="en">o033-Department-1</departmentName><communicationInfo><email>o033-email-1@de.de</email><email>o033-email-3@de.de</email><url>http://o033-url-1.de</url><url>http://o033-url-2.de</url><address>o033-Address</address><zipCode>o033-zip</zipCode><city>o033-City</city><region>o033-Region</region><country>o033-Country</country><telephoneNumber>o033-Telephone-1</telephoneNumber><telephoneNumber>o033-Telephone-2</telephoneNumber><faxNumber>o033-Fax-1</faxNumber><faxNumber>o033-Fax-2</faxNumber></communicationInfo></affiliation></personInfo></annotator><annotator><personInfo><surname lang="en">p034-Surname-1</surname><givenName lang="en">p034-Given name-1</givenName><sex>female</sex><communicationInfo><email>p034-email-1@de.de</email><email>p034-email-2@de.de</email><url>http://p034-url-1.de</url><url>http://p034-url-2.de</url><address>p034-Address</address><zipCode>p034-Zip code</zipCode><city>p034-City</city><region>p034-Region</region><country>p034-Country</country><telephoneNumber>p034-Telephone-1</telephoneNumber><telephoneNumber>p034-Telephone-2</telephoneNumber><faxNumber>p034-Fax-1</faxNumber><faxNumber>p034-Fax-2</faxNumber></communicationInfo><position>p034-Position</position><affiliation><organizationName lang="de">o034-name-2</organizationName><organizationName lang="en">o034-name-1</organizationName><organizationShortName lang="de">o034-short-2</organizationShortName><organizationShortName lang="en">o034-short-1</organizationShortName><departmentName lang="de">o034-Department-2</departmentName><departmentName lang="en">o034-Department-1</departmentName><communicationInfo><email>o034-email-1@de.de</email><email>o034-email-3@de.de</email><url>http://o034-url-1.de</url><url>http://o034-url-2.de</url><address>o034-Address</address><zipCode>o034-zip</zipCode><city>o034-City</city><region>o034-Region</region><country>o034-Country</country><telephoneNumber>o034-Telephone-1</telephoneNumber><telephoneNumber>o034-Telephone-2</telephoneNumber><faxNumber>o034-Fax-1</faxNumber><faxNumber>o034-Fax-2</faxNumber></communicationInfo></affiliation></personInfo></annotator></annotationInfo><annotationInfo><annotationType>syntacticosemanticAnnotation-links</annotationType><annotatedElements>backgroundNoise</annotatedElements><annotatedElements>discourseMarkers</annotatedElements><annotationStandoff>false</annotationStandoff><segmentationLevel>shot</segmentationLevel><segmentationLevel>utterance</segmentationLevel><annotationFormat>annotaformat83495043</annotationFormat><tagset>tagest568594043095</tagset><tagsetLanguageId>ter</tagsetLanguageId><tagsetLanguageName>Tereno</tagsetLanguageName><conformanceToStandardsBestPractices>SRX</conformanceToStandardsBestPractices><conformanceToStandardsBestPractices>XLIFF</conformanceToStandardsBestPractices><theoreticModel>theoreticmodel4395803402022</theoreticModel><annotationManual><documentInfo><documentType>article</documentType><title lang="de">doc024-title-2</title><title lang="en">doc024-title-1</title><author>doc024-author-1</author><author>doc024-author-2</author><editor>doc024-editor-1</editor><editor>doc024-editor-2</editor><year>2000</year><publisher>doc024-pub-1</publisher><publisher>doc024-pub-2</publisher><bookTitle>doc024-Book title</bookTitle><journal>doc024-journal</journal><volume>doc024-volume</volume><series>doc024-series</series><pages>doc024-pages</pages><edition>doc024-edition</edition><conference>doc024-conference</conference><doi>doc024-doi</doi><url>http://doc024-url.de</url><ISSN>doc024-issn</ISSN><ISBN>doc024-isbn</ISBN><keywords>doc024-key-1</keywords><keywords>doc024-key-2</keywords><documentLanguageName>English</documentLanguageName><documentLanguageId>en</documentLanguageId></documentInfo></annotationManual><annotationManual><documentInfo><documentType>article</documentType><title lang="de">doc025-title-2</title><title lang="en">doc025-title-1</title><author>doc025-author-1</author><author>doc025-author-2</author><editor>doc025-editor-1</editor><editor>doc025-editor-2</editor><year>2000</year><publisher>doc025-pub-1</publisher><publisher>doc025-pub-2</publisher><bookTitle>doc025-Book title</bookTitle><journal>doc025-journal</journal><volume>doc025-volume</volume><series>doc025-series</series><pages>doc025-pages</pages><edition>doc025-edition</edition><conference>doc025-conference</conference><doi>doc025-doi</doi><url>http://doc025-url.de</url><ISSN>doc025-issn</ISSN><ISBN>doc025-isbn</ISBN><keywords>doc025-key-1</keywords><keywords>doc025-key-2</keywords><documentLanguageName>English</documentLanguageName><documentLanguageId>en</documentLanguageId></documentInfo></annotationManual><annotationMode>interactive</annotationMode><annotationModeDetails>annotationmodedetials4305843</annotationModeDetails><annotationTool><targetResourceNameURI>annotatool8234594305043</targetResourceNameURI></annotationTool><annotationTool><targetResourceNameURI>annotatoool45905045</targetResourceNameURI></annotationTool><annotationStartDate>2012-04-08</annotationStartDate><annotationEndDate>2012-07-30</annotationEndDate><sizePerAnnotation><size>356497899089</size><sizeUnit>predicates</sizeUnit></sizePerAnnotation><interannotatorAgreement>interannotagree83406954</interannotatorAgreement><intraannotatorAgreement>intraano348590456045</intraannotatorAgreement><annotator><organizationInfo><organizationName lang="de">org031-name-2</organizationName><organizationName lang="en">org031-name-1</organizationName><organizationShortName lang="de">org031-short-2</organizationShortName><organizationShortName lang="en">org031-short-1</organizationShortName><departmentName lang="de">org031-Department-2</departmentName><departmentName lang="en">org031-Department-1</departmentName><communicationInfo><email>org031-email-1@de.de</email><email>org031-email-2@de.de</email><url>http://org031-url-1.de</url><url>http://org031-url-2.de</url><address>org031-Address</address><zipCode>org031-zip</zipCode><city>org031-City</city><region>org031-Region</region><country>org031-Country</country><telephoneNumber>org031-Telephone-1</telephoneNumber><telephoneNumber>org031-Telephone-2</telephoneNumber><faxNumber>org031-Fax-1</faxNumber><faxNumber>org031-Fax-2</faxNumber></communicationInfo></organizationInfo></annotator><annotator><organizationInfo><organizationName lang="de">org032-name-2</organizationName><organizationName lang="en">org032-name-1</organizationName><organizationShortName lang="de">org032-short-2</organizationShortName><organizationShortName lang="en">org032-short-1</organizationShortName><departmentName lang="de">org032-Department-2</departmentName><departmentName lang="en">org032-Department-1</departmentName><communicationInfo><email>org032-email-1@de.de</email><email>org032-email-2@de.de</email><url>http://org032-url-1.de</url><url>http://org032-url-2.de</url><address>org032-Address</address><zipCode>org032-zip</zipCode><city>org032-City</city><region>org032-Region</region><country>org032-Country</country><telephoneNumber>org032-Telephone-1</telephoneNumber><telephoneNumber>org032-Telephone-2</telephoneNumber><faxNumber>org032-Fax-1</faxNumber><faxNumber>org032-Fax-2</faxNumber></communicationInfo></organizationInfo></annotator></annotationInfo><annotationInfo><annotationType>semanticAnnotation-questionTopicalTarget</annotationType></annotationInfo><domainInfo><domain>domain439580345</domain><sizePerDomain><size>3457567</size><sizeUnit>entries</sizeUnit></sizePerDomain><conformanceToClassificationScheme>MeSH_classification</conformanceToClassificationScheme></domainInfo><domainInfo><domain>domain3948043</domain><sizePerDomain><size>24365744</size><sizeUnit>diphones</sizeUnit></sizePerDomain><conformanceToClassificationScheme>ANC_genreClassification</conformanceToClassificationScheme></domainInfo><timeCoverageInfo><timeCoverage>timecoverage84399034</timeCoverage><sizePerTimeCoverage><size>364357567</size><sizeUnit>phoneticUnits</sizeUnit></sizePerTimeCoverage></timeCoverageInfo><timeCoverageInfo><timeCoverage>timecoverage9435000</timeCoverage><sizePerTimeCoverage><size>346456436</size><sizeUnit>lexicalTypes</sizeUnit></sizePerTimeCoverage></timeCoverageInfo><geographicCoverageInfo><geographicCoverage>geocoverage94358099</geographicCoverage><sizePerGeographicCoverage><size>4745878978</size><sizeUnit>phonemes</sizeUnit></sizePerGeographicCoverage></geographicCoverageInfo><geographicCoverageInfo><geographicCoverage>geocoverage4309500043</geographicCoverage><sizePerGeographicCoverage><size>47</size><sizeUnit>4-grams</sizeUnit></sizePerGeographicCoverage></geographicCoverageInfo><imageClassificationInfo><imageGenre>imagegenere03459034</imageGenre><subject_topic>subjectto94305890</subject_topic><conformanceToClassificationScheme>BNC_domainClassification</conformanceToClassificationScheme><sizePerImageClassification><size>93846095845009090909</size><sizeUnit>gb</sizeUnit></sizePerImageClassification></imageClassificationInfo><imageClassificationInfo><imageGenre>imagegenre0439059ß456</imageGenre><subject_topic>subjecttop9345809546</subject_topic><conformanceToClassificationScheme>NLK_classification</conformanceToClassificationScheme><sizePerImageClassification><size>68906890890789</size><sizeUnit>phoneticUnits</sizeUnit></sizePerImageClassification></imageClassificationInfo><captureInfo><capturingDeviceType>closeTalkMicrophone</capturingDeviceType><capturingDeviceType>microphoneArray</capturingDeviceType><capturingDeviceType>telephoneIP</capturingDeviceType><capturingDeviceTypeDetails>captudevicetedetails9435034</capturingDeviceTypeDetails><capturingDetails>CAPTDETAILS$§%)(§=$)890354890</capturingDetails><capturingEnvironment>plain</capturingEnvironment><sensorTechnology>sensortechnolo 943580345</sensorTechnology><sensorTechnology>sensortechnolo439580</sensorTechnology><sceneIllumination>other</sceneIllumination><personSourceSetInfo><numberOfPersons>6456</numberOfPersons><ageOfPersons>adult</ageOfPersons><ageOfPersons>elderly</ageOfPersons><ageRangeStart>43</ageRangeStart><ageRangeEnd>67</ageRangeEnd><sexOfPersons>male</sexOfPersons><originOfPersons>mixed</originOfPersons><dialectAccentOfPersons>dialaccper4305040400</dialectAccentOfPersons><dialectAccentOfPersons>dialaccper043590233</dialectAccentOfPersons><geographicDistributionOfPersons>geodiscof per4509345</geographicDistributionOfPersons><hearingImpairmentOfPersons>no</hearingImpairmentOfPersons><speakingImpairmentOfPersons>mixed</speakingImpairmentOfPersons><numberOfTrainedSpeakers>453</numberOfTrainedSpeakers><speechInfluences>hyperbaric</speechInfluences><speechInfluences>medication</speechInfluences><participantInfo><alias lang="en">alias945990430</alias><alias lang="chn">alias4309900934</alias><ageGroup>child</ageGroup><age>49</age><sex>unknown</sex><origin>nonNative</origin><placeOfLiving>placeoflving4359094309</placeOfLiving><placeOfBirth>placeofbirth390943</placeOfBirth><placeOfChildhood>placeofchildhood53546</placeOfChildhood><dialectAccent lang="en">dialaccent43949</dialectAccent><dialectAccent lang="art">dialaccetn03405904</dialectAccent><speakingImpairment>speakingimpair094359</speakingImpairment><hearingImpairment>hearingim43509034</hearingImpairment><smokingHabits>smokinhabi030490</smokingHabits><vocalTractConditions>dentalProsthesis</vocalTractConditions><profession>profession43509090</profession><height>10930</height><weight>8409</weight><trainedSpeaker>true</trainedSpeaker><placeOfSecondEducation>palaceof seoc edu43 09</placeOfSecondEducation><educationLevel>education level43500</educationLevel></participantInfo><participantInfo><alias lang="en">alias99430</alias><alias lang="afa">alias0043004</alias><ageGroup>teenager</ageGroup><age>43</age><sex>male</sex><origin>nonNative</origin><placeOfLiving>placeofliving94399</placeOfLiving><placeOfBirth>pkaceofbirth345003</placeOfBirth><placeOfChildhood>placeofchild045900439</placeOfChildhood><dialectAccent lang="en">dialectaccent00404</dialectAccent><dialectAccent lang="cus">dialectaccent45456</dialectAccent><speakingImpairment>speaking impra34500439</speakingImpairment><hearingImpairment>hearing impari0039450</hearingImpairment><smokingHabits>smoking habits 9234890</smokingHabits><vocalTractConditions>other</vocalTractConditions><profession>profession 4395034</profession><height>312</height><weight>325</weight><trainedSpeaker>false</trainedSpeaker><placeOfSecondEducation>placeofseconeducation4300</placeOfSecondEducation><educationLevel>educationlevel439500</educationLevel></participantInfo></personSourceSetInfo></captureInfo><creationInfo><originalSource><targetResourceNameURI>targetreousnameuri3485054</targetResourceNameURI></originalSource><originalSource><targetResourceNameURI>targetresiourcenameuri3485034</targetResourceNameURI></originalSource><creationMode>manual</creationMode><creationModeDetails>creationmodedetailas040504</creationModeDetails><creationTool><targetResourceNameURI>creationtool34095954</targetResourceNameURI></creationTool><creationTool><targetResourceNameURI>creationtool43965804055454</targetResourceNameURI></creationTool></creationInfo><linkToOtherMediaInfo><otherMedia>textNumerical</otherMedia><mediaTypeDetails>mdeiadetials0450930443</mediaTypeDetails><synchronizedWithText>true</synchronizedWithText><synchronizedWithAudio>true</synchronizedWithAudio><synchronizedWithVideo>true</synchronizedWithVideo><sycnhronizedWithImage>true</sycnhronizedWithImage><synchronizedWithTextNumerical>true</synchronizedWithTextNumerical></linkToOtherMediaInfo><linkToOtherMediaInfo><otherMedia>audio</otherMedia><mediaTypeDetails>mediadetails43589400</mediaTypeDetails><synchronizedWithText>false</synchronizedWithText><synchronizedWithAudio>false</synchronizedWithAudio><synchronizedWithVideo>false</synchronizedWithVideo><sycnhronizedWithImage>false</sycnhronizedWithImage><synchronizedWithTextNumerical>false</synchronizedWithTextNumerical></linkToOtherMediaInfo></corpusImageInfo></corpusMediaType></corpusInfo></resourceComponentType></resourceInfo>